pt_text_selector/__init__.py
pt_text_selector/main.py
pt_text_selector/paratextTextPicker.py
paratext_text_selector-0.3.3.dist-info/LICENSE
paratext_text_selector-0.3.3.dist-info/METADATA
paratext_text_selector-0.3.3.dist-info/WHEEL
paratext_text_selector-0.3.3.dist-info/entry_points.txt
paratext_text_selector-0.3.3.dist-info/top_level.txt
paratext_text_selector-0.3.3.dist-info/RECORD
