Metadata-Version: 2.1
Name: paratext-text-selector
Version: 0.3.3
Summary: Python tool for selecting books and portions of books created with Paratext
Home-page: UNKNOWN
License: MIT
Platform: UNKNOWN
